duckduckgo_mcp_server/__init__.py
duckduckgo_mcp_server/server.py
duckduckgo_mcp_server_sse-0.1.1.post1.dist-info/METADATA
duckduckgo_mcp_server_sse-0.1.1.post1.dist-info/WHEEL
duckduckgo_mcp_server_sse-0.1.1.post1.dist-info/entry_points.txt
duckduckgo_mcp_server_sse-0.1.1.post1.dist-info/licenses/LICENSE
duckduckgo_mcp_server_sse-0.1.1.post1.dist-info/RECORD
