Metadata-Version: 2.4
Name: duckduckgo-mcp-server-sse
Version: 0.1.1.post1
Summary: MCP Server (SSE) for searching via DuckDuckGo
Project-URL: Homepage, https://github.com/wildoranges/duckduckgo-mcp-server-sse
Project-URL: Issues, https://github.com/wildoranges/duckduckgo-mcp-server-sse/issues
Author-email: Nick Clyde <nick@clyde.tech>, wildoranges <zkd18cjb@mail.ustc.edu.cn>
License-Expression: MIT
License-File: LICENSE
Keywords: duckduckgo,http,mcp,search,sse,web-search
Classifier: Development Status :: 3 - Alpha
Classifier: Intended Audience :: Developers
Classifier: License :: OSI Approved :: MIT License
Classifier: Programming Language :: Python :: 3
Classifier: Programming Language :: Python :: 3.10
Classifier: Programming Language :: Python :: 3.11
Classifier: Programming Language :: Python :: 3.12
Classifier: Programming Language :: Python :: 3.13
Requires-Python: >=3.10
Requires-Dist: beautifulsoup4>=4.13.3
Requires-Dist: httpx>=0.28.1
Requires-Dist: mcp[cli]>=1.3.0
